<?xml version="1.0" encoding="utf-8"?>
<PlayerDatabase>
  <PlayerEntry>
    <playerName>Pocchi</playerName>
    <playerRole>Warrior</playerRole>
    <playerGender>Male</playerGender>
    <playerLevel>1</playerLevel>
    <playerExp>0</playerExp>
  </PlayerEntry>
  <PlayerEntry>
    <playerName>Diego</playerName>
    <playerRole>Wizard</playerRole>
    <playerGender>Male</playerGender>
    <playerLevel>1</playerLevel>
    <playerExp>0</playerExp>
  </PlayerEntry>
  <PlayerEntry>
    <playerName>Caleb</playerName>
    <playerRole>Wizard</playerRole>
    <playerGender>Female</playerGender>
    <playerLevel>1</playerLevel>
    <playerExp>0</playerExp>
  </PlayerEntry>
  <PlayerEntry>
    <playerName>Jackson</playerName>
    <playerRole>Hero</playerRole>
    <playerGender>Male</playerGender>
    <playerLevel>1</playerLevel>
    <playerExp>0</playerExp>
  </PlayerEntry>
  <PlayerEntry>
    <playerName>Yevi</playerName>
    <playerRole>Healer</playerRole>
    <playerGender>Female</playerGender>
    <playerLevel>1</playerLevel>
    <playerExp>0</playerExp>
  </PlayerEntry>
</PlayerDatabase>